{"tasks":[{"name":"epic","description":"epic","complete":false},{"name":"Mow Lawn","description":"Mow the lawn","complete":false,"dueDate":"2026-05-10","person":{"age":56,"name":"Jack Ryan","relation":"Father"}},{"name":"Moving","description":"Help with moving","complete":false,"dueDate":"2024-10-09","person":{"age":41,"name":"Jim Bonacci","relation":"Acquaintance"}},{"name":"another thig","description":"texthere","complete":false,"person":{"age":25,"name":"John Doe","relation":"Cousin"}},{"name":"Walk dog","description":"walk the dog","complete":false,"dueDate":"2022-01-04","person":{"age":25,"name":"John Doe","relation":"Cousin"}},{"name":"Homecoming","description":"Homecoming","complete":false,"person":{"age":25,"name":"John Doe","relation":"Cousin"}}],"people":[{"age":25,"name":"John Doe","relation":"Cousin"},{"age":41,"name":"Jim Bonacci","relation":"Acquaintance"},{"age":56,"name":"Jack Ryan","relation":"Father"}]}